{
  "module": "automation",
  "func": "AutomationEngine.load_image_cv2",
  "kind": "method",
  "name": "load_image_cv2",
  "filename": "<frozen automation>",
  "argcount": 3,
  "nlocals": 7,
  "stacksize": 7,
  "flags": 536870915,
  "names": [
    "np",
    "fromfile",
    "uint8",
    "cv2",
    "imdecode",
    "Exception",
    "log"
  ],
  "varnames": [
    "self",
    "image_path",
    "flags",
    "__assert_armored__",
    "_var_var_167",
    "_var_var_168",
    "_var_var_3"
  ],
  "cellvars": [],
  "freevars": [],
  "consts": [
    {
      "type": "str",
      "value": "加载图片（支持中文路径）"
    },
    {
      "type": "builtin"
    },
    {
      "type": "builtin"
    },
    {
      "type": "bytes",
      "len": 20
    },
    {
      "type": "tuple",
      "len": 1
    },
    {
      "type": "builtin"
    },
    {
      "type": "str",
      "value": "加载图片失败: "
    },
    {
      "type": "str",
      "value": ", 错误: "
    },
    {
      "type": "None"
    }
  ]
}